GenericDataSaver/GenericDataSaver.py
GenericDataSaver/__init__.py
genericdatasaver-0.2.5.dist-info/METADATA
genericdatasaver-0.2.5.dist-info/WHEEL
genericdatasaver-0.2.5.dist-info/top_level.txt
genericdatasaver-0.2.5.dist-info/RECORD
