Metadata-Version: 2.4
Name: GenericDataSaver
Version: 0.2.5
Summary: Saves Data, Don't use it in production cuz it's not secure and it's just my hobby project
Author: MondayStuff
Author-email: MondayStuff <Hoangquocanhmon@icloud.com>
Classifier: Programming Language :: Python :: 3
Classifier: Operating System :: OS Independent
Requires-Python: >=3.0
Dynamic: author
Dynamic: requires-python
